ecommerce_worker/__init__.py
ecommerce_worker/cache.py
ecommerce_worker/celery_app.py
ecommerce_worker/utils.py
ecommerce_worker/configuration/__init__.py
ecommerce_worker/configuration/base.py
ecommerce_worker/configuration/devstack.py
ecommerce_worker/configuration/local.py
ecommerce_worker/configuration/logger.py
ecommerce_worker/configuration/production.py
ecommerce_worker/configuration/test.py
ecommerce_worker/email/__init__.py
ecommerce_worker/email/v1/__init__.py
ecommerce_worker/email/v1/api.py
ecommerce_worker/email/v1/tasks.py
ecommerce_worker/email/v1/utils.py
ecommerce_worker/email/v1/braze/__init__.py
ecommerce_worker/email/v1/braze/client.py
ecommerce_worker/email/v1/braze/exceptions.py
ecommerce_worker/email/v1/braze/tasks.py
ecommerce_worker/fulfillment/__init__.py
ecommerce_worker/fulfillment/v1/__init__.py
ecommerce_worker/fulfillment/v1/tasks.py
edx_ecommerce_worker-3.3.4.dist-info/LICENSE.txt
edx_ecommerce_worker-3.3.4.dist-info/METADATA
edx_ecommerce_worker-3.3.4.dist-info/WHEEL
edx_ecommerce_worker-3.3.4.dist-info/top_level.txt
edx_ecommerce_worker-3.3.4.dist-info/RECORD
