Metadata-Version: 2.1
Name: edx-ecommerce-worker
Version: 3.3.4
Summary: Celery tasks supporting the operations of edX's ecommerce service
Home-page: https://github.com/openedx/ecommerce-worker
Author: edX
Author-email: oscm@edx.org
License: AGPL
Keywords: edx ecommerce worker
Platform: UNKNOWN
Classifier: Development Status :: 3 - Alpha
Classifier: License :: OSI Approved :: GNU Affero General Public License v3
Classifier: Programming Language :: Python
Classifier: Programming Language :: Python :: 3.8
Classifier: Topic :: Internet
Classifier: Intended Audience :: Developers
Classifier: Environment :: Web Environment
Requires-Dist: six
Requires-Dist: celery
Requires-Dist: edx-braze-client
Requires-Dist: redis
Requires-Dist: edx-rest-api-client
